Flask_Matomo-1.0.1.dist-info/DESCRIPTION.rst
Flask_Matomo-1.0.1.dist-info/METADATA
Flask_Matomo-1.0.1.dist-info/RECORD
Flask_Matomo-1.0.1.dist-info/WHEEL
Flask_Matomo-1.0.1.dist-info/metadata.json
Flask_Matomo-1.0.1.dist-info/top_level.txt
flask_matomo/__init__.py
flask_matomo/core.py
