Metadata-Version: 2.0
Name: Flask-Matomo
Version: 1.0.1
Summary: Track requests to your Flask website with Matomo 
Home-page: https://github.com/Lanseuo/flask-matomo
Author: Lucas Hild
Author-email: contact@lucas-hild.de
License: MIT
Platform: UNKNOWN
Classifier: Environment :: Web Environment
Classifier: Intended Audience :: Developers
Classifier: License :: OSI Approved :: MIT License
Classifier: Operating System :: OS Independent
Classifier: Programming Language :: Python
Classifier: Topic :: Internet :: WWW/HTTP :: Dynamic Content
Classifier: Topic :: Software Development :: Libraries :: Python Modules
Requires-Dist: Flask
